<?xml version="1.0" encoding="UTF-8"?>
<flow id="f7e98d9a-21d9-484a-a9f6-fb3a4b29e00e">
  <descriptionCdata><![CDATA[]]></descriptionCdata>
  <annotation></annotation>
  <name>flow</name>
  <categories/>
  <inputs/>
  <possibleResponses/>
  <availableResultExpressions/>
  <resultExpression id="55ea02c3-5270-4179-9ca6-e26df4b0d528">
    <annotation></annotation>
    <name>FailureMessage</name>
    <fieldName>FailureMessage</fieldName>
    <sourceType>RAWRESULT</sourceType>
    <filters/>
  </resultExpression>
  <iconSpec id="dad23241-8d68-4c2d-991b-9a29fddb0924">
    <baseIcon>flow.png</baseIcon>
    <basePath>System</basePath>
    <readOnly>false</readOnly>
    <layers/>
  </iconSpec>
  <callouts/>
  <checkPointFlow>true</checkPointFlow>
  <compatibleRuntimeContext>false</compatibleRuntimeContext>
  <historyCheckPointFlow>true</historyCheckPointFlow>
  <steps/>
</flow>