<?xml version="1.0" encoding="UTF-8"?>
<flow id="f082b32c-c9b0-4a15-84db-8e6af3db0cfc">
  <descriptionCdata><![CDATA[]]></descriptionCdata>
  <annotation></annotation>
  <name>flow</name>
  <categories/>
  <inputs/>
  <possibleResponses/>
  <availableResultExpressions/>
  <resultExpression id="168cd2cf-35ec-4aea-b2df-d11a5218b68f">
    <annotation></annotation>
    <name>FailureMessage</name>
    <fieldName>FailureMessage</fieldName>
    <sourceType>RAWRESULT</sourceType>
    <filters/>
  </resultExpression>
  <iconSpec id="05c4c806-42b5-4605-b2e3-2a1cb206385c">
    <baseIcon>flow.png</baseIcon>
    <basePath>System</basePath>
    <readOnly>false</readOnly>
    <layers/>
  </iconSpec>
  <callouts/>
  <checkPointFlow>true</checkPointFlow>
  <compatibleRuntimeContext>false</compatibleRuntimeContext>
  <historyCheckPointFlow>true</historyCheckPointFlow>
  <steps/>
</flow>