<?xml version="1.0" encoding="UTF-8"?>
<flow id="a2bd8679-0da5-4335-a9ad-d4575f804c85">
  <descriptionCdata><![CDATA[]]></descriptionCdata>
  <annotation></annotation>
  <name>flow</name>
  <categories/>
  <inputs/>
  <possibleResponses/>
  <availableResultExpressions/>
  <resultExpression id="68d3f22a-1a3c-458f-ad74-14b7880a51cc">
    <annotation></annotation>
    <name>FailureMessage</name>
    <fieldName>FailureMessage</fieldName>
    <sourceType>RAWRESULT</sourceType>
    <filters/>
  </resultExpression>
  <iconSpec id="5d28a31d-6170-4616-b522-c6c6be05a827">
    <baseIcon>flow.png</baseIcon>
    <basePath>System</basePath>
    <readOnly>false</readOnly>
    <layers/>
  </iconSpec>
  <callouts/>
  <checkPointFlow>true</checkPointFlow>
  <compatibleRuntimeContext>false</compatibleRuntimeContext>
  <historyCheckPointFlow>true</historyCheckPointFlow>
  <steps/>
</flow>