<?xml version="1.0" encoding="UTF-8"?>
<flow id="aee0f0dd-497a-476a-bfa7-3c2942bfe424">
  <descriptionCdata><![CDATA[]]></descriptionCdata>
  <annotation></annotation>
  <name>flow</name>
  <categories/>
  <inputs/>
  <possibleResponses/>
  <availableResultExpressions/>
  <resultExpression id="60d1472b-36ec-4e87-ac8b-b0c986da93ce">
    <annotation></annotation>
    <name>FailureMessage</name>
    <fieldName>FailureMessage</fieldName>
    <sourceType>RAWRESULT</sourceType>
    <filters/>
  </resultExpression>
  <iconSpec id="4cfed99a-9b3b-47b9-bd65-d14f956711a7">
    <baseIcon>flow.png</baseIcon>
    <basePath>System</basePath>
    <readOnly>false</readOnly>
    <layers/>
  </iconSpec>
  <callouts/>
  <checkPointFlow>true</checkPointFlow>
  <compatibleRuntimeContext>false</compatibleRuntimeContext>
  <historyCheckPointFlow>true</historyCheckPointFlow>
  <steps/>
</flow>