<?xml version="1.0" encoding="UTF-8"?>
<flow id="e1a0534f-3eb2-4d9a-8f78-83648dd0ae18">
  <descriptionCdata><![CDATA[]]></descriptionCdata>
  <annotation></annotation>
  <name>flow</name>
  <categories/>
  <inputs/>
  <possibleResponses/>
  <availableResultExpressions/>
  <resultExpression id="5355aba7-afc7-4cb0-8af1-c53aadfc5a33">
    <annotation></annotation>
    <name>FailureMessage</name>
    <fieldName>FailureMessage</fieldName>
    <sourceType>RAWRESULT</sourceType>
    <filters/>
  </resultExpression>
  <iconSpec id="b80858b0-a01d-4d83-9707-b5f07b4eaf3d">
    <baseIcon>flow.png</baseIcon>
    <basePath>System</basePath>
    <readOnly>false</readOnly>
    <layers/>
  </iconSpec>
  <callouts/>
  <checkPointFlow>true</checkPointFlow>
  <compatibleRuntimeContext>false</compatibleRuntimeContext>
  <historyCheckPointFlow>true</historyCheckPointFlow>
  <steps/>
</flow>